{
    "gui_light": "side",
    "display": {
        "gui": {
            "rotation": [
                30,
                225,
                0
            ],
            "translation": [
                0,
                0,
                0
            ],
            "scale": [
                0.625,
                0.625,
                0.625
            ]
        },
        "ground": {
            "rotation": [
                0,
                0,
                0
            ],
            "translation": [
                0,
                3,
                0
            ],
            "scale": [
                0.25,
                0.25,
                0.25
            ]
        },
        "fixed": {
            "rotation": [
                0,
                0,
                0
            ],
            "translation": [
                0,
                0,
                0
            ],
            "scale": [
                0.5,
                0.5,
                0.5
            ]
        },
        "on_shelf": {
            "rotation": [
                0,
                180,
                0
            ],
            "translation": [
                0,
                0,
                0
            ],
            "scale": [
                1,
                1,
                1
            ]
        },
        "thirdperson_righthand": {
            "rotation": [
                75,
                45,
                0
            ],
            "translation": [
                0,
                2,
                0.5
            ],
            "scale": [
                0.4,
                0.4,
                0.4
            ]
        },
        "firstperson_righthand": {
            "rotation": [
                0,
                45,
                0
            ],
            "translation": [
                0,
                0,
                0
            ],
            "scale": [
                0.4,
                0.4,
                0.4
            ]
        },
        "firstperson_lefthand": {
            "rotation": [
                0,
                225,
                0
            ],
            "translation": [
                0,
                0,
                0
            ],
            "scale": [
                0.4,
                0.4,
                0.4
            ]
        },
        "head": {
            "rotation": [
                -180,
                0,
                0
            ],
            "translation": [
                8.5,
                4,
                0
            ]
        }
    },
    "elements": [
        {
            "from": [
                6,
                12,
                6
            ],
            "to": [
                10,
                16,
                10
            ],
            "faces": {
                "north": {
                    "uv": [
                        0,
                        0,
                        4,
                        4
                    ],
                    "texture": "weathered_lightning_rod"
                },
                "south": {
                    "uv": [
                        0,
                        0,
                        4,
                        4
                    ],
                    "texture": "weathered_lightning_rod"
                },
                "west": {
                    "uv": [
                        0,
                        0,
                        4,
                        4
                    ],
                    "texture": "weathered_lightning_rod"
                },
                "east": {
                    "uv": [
                        0,
                        0,
                        4,
                        4
                    ],
                    "texture": "weathered_lightning_rod"
                },
                "down": {
                    "uv": [
                        0,
                        0,
                        4,
                        4
                    ],
                    "texture": "weathered_lightning_rod"
                },
                "up": {
                    "uv": [
                        4,
                        4,
                        0,
                        0
                    ],
                    "texture": "weathered_lightning_rod"
                }
            }
        },
        {
            "from": [
                7,
                0,
                7
            ],
            "to": [
                9,
                12,
                9
            ],
            "faces": {
                "north": {
                    "uv": [
                        0,
                        4,
                        2,
                        16
                    ],
                    "texture": "weathered_lightning_rod"
                },
                "south": {
                    "uv": [
                        0,
                        4,
                        2,
                        16
                    ],
                    "texture": "weathered_lightning_rod"
                },
                "west": {
                    "uv": [
                        0,
                        4,
                        2,
                        16
                    ],
                    "texture": "weathered_lightning_rod"
                },
                "east": {
                    "uv": [
                        0,
                        4,
                        2,
                        16
                    ],
                    "texture": "weathered_lightning_rod"
                },
                "down": {
                    "uv": [
                        0,
                        4,
                        2,
                        6
                    ],
                    "texture": "weathered_lightning_rod"
                }
            }
        }
    ]
}